README.rst
setup.py
rlscore/__init__.py
rlscore.egg-info/PKG-INFO
rlscore.egg-info/SOURCES.txt
rlscore.egg-info/dependency_links.txt
rlscore.egg-info/top_level.txt
rlscore/kernel/__init__.py
rlscore/kernel/gaussian_kernel.py
rlscore/kernel/linear_kernel.py
rlscore/kernel/polynomial_kernel.py
rlscore/kernel/rset_kernel.py
rlscore/learner/__init__.py
rlscore/learner/_global_rankrls.c
rlscore/learner/_greedy_rls.c
rlscore/learner/_interactive_rls_classifier.c
rlscore/learner/_rls.c
rlscore/learner/_steepest_descent_mmc.c
rlscore/learner/_two_step_rls.c
rlscore/learner/cg_kron_rls.py
rlscore/learner/cg_rankrls.py
rlscore/learner/cg_rls.py
rlscore/learner/global_rankrls.py
rlscore/learner/greedy_nfold_rls.py
rlscore/learner/greedy_rls.py
rlscore/learner/interactive_rls_classifier.py
rlscore/learner/kron_rls.py
rlscore/learner/kron_svm.py
rlscore/learner/mmc.py
rlscore/learner/query_rankrls.py
rlscore/learner/rankrls_with_pairwise_preferences.py
rlscore/learner/rls.py
rlscore/learner/space_efficient_greedy_rls.py
rlscore/learner/steepest_descent_mmc.py
rlscore/learner/two_step_rls.py
rlscore/measure/__init__.py
rlscore/measure/accuracy_measure.py
rlscore/measure/auc_measure.py
rlscore/measure/cindex_measure.py
rlscore/measure/fscore_measure.py
rlscore/measure/measure_utilities.py
rlscore/measure/multi_accuracy_measure.py
rlscore/measure/spearman_measure.py
rlscore/measure/sq_mprank_measure.py
rlscore/measure/sqerror_measure.py
rlscore/predictor/__init__.py
rlscore/predictor/pairwise_predictor.py
rlscore/predictor/predictor.py
rlscore/test/__init__.py
rlscore/test/legacy_test.py
rlscore/test/test.py
rlscore/test/test_model.py
rlscore/test/test_kernel/__init__.py
rlscore/test/test_kernel/test_gaussian.py
rlscore/test/test_kernel/test_linear.py
rlscore/test/test_kernel/test_polynomial.py
rlscore/test/test_learner/__init__.py
rlscore/test/test_learner/test_cg_kron_rls.py
rlscore/test/test_learner/test_cg_rankrls.py
rlscore/test/test_learner/test_cg_rls.py
rlscore/test/test_learner/test_global_rankrls.py
rlscore/test/test_learner/test_greedy_nfold_rls.py
