Metadata-Version: 1.0
Name: rlscore
Version: 0.8.1
Summary: machine learning package
Home-page: https://github.com/aatapa/RLScore
Author: UNKNOWN
Author-email: UNKNOWN
License: MIT
Platform: UNKNOWN
